serializor-2.1.0.dist-info/METADATA
serializor-2.1.0.dist-info/top_level.txt
serializor-2.1.0.dist-info/WHEEL
serializor-2.1.0.dist-info/RECORD
serializor-2.1.0.dist-info/licenses/LICENSE
serializor/ser.pyi
serializor/__init__.pxd
serializor/utils.py
serializor/utils.pxd
serializor/ser.cpython-311-x86_64-linux-musl.so
serializor/typeref.py
serializor/identifier.cpython-311-x86_64-linux-musl.so
serializor/typeref.c
serializor/identifier.py
serializor/typeref.cpython-311-x86_64-linux-musl.so
serializor/des.py
serializor/__init__.py
serializor/utils.pyi
serializor/utils.c
serializor/crypto.pxd
serializor/ser.pxd
serializor/ser.py
serializor/ser.c
serializor/errors.py
serializor/utils.cpython-311-x86_64-linux-musl.so
serializor/identifier.c
serializor/des.c
serializor/crypto.py
serializor/typeref.pxd
serializor/crypto.cpython-311-x86_64-linux-musl.so
serializor/des.pxd
serializor/des.cpython-311-x86_64-linux-musl.so
serializor/identifier.pxd
serializor/crypto.c
serializor/unicode/ser.pyi
serializor/unicode/__init__.pxd
serializor/unicode/ser.cpython-311-x86_64-linux-musl.so
serializor/unicode/des.pyi
serializor/unicode/des.py
serializor/unicode/__init__.py
serializor/unicode/ser.pxd
serializor/unicode/ser.py
serializor/unicode/ser.c
serializor/unicode/des.c
serializor/unicode/des.pxd
serializor/unicode/des.cpython-311-x86_64-linux-musl.so
serializor/binary/ser.pyi
serializor/binary/__init__.pxd
serializor/binary/ser.cpython-311-x86_64-linux-musl.so
serializor/binary/des.pyi
serializor/binary/des.py
serializor/binary/__init__.py
serializor/binary/ser.pxd
serializor/binary/ser.py
serializor/binary/ser.c
serializor/binary/des.c
serializor/binary/des.pxd
serializor/binary/des.cpython-311-x86_64-linux-musl.so
