Metadata-Version: 2.4
Name: serializor
Version: 2.1.0
Summary: Serialization/Deserialization for Python native and NumPy/Pandas objects.
Home-page: https://github.com/AresJef/Serializor
Author: Jiefu Chen
Author-email: keppa1991@163.com
License: MIT license, Apache License 2.0
Keywords: serialize,serialization,numpy,pandas,python,deserialize,deserialization
Classifier: Programming Language :: Python :: 3
Classifier: Operating System :: Unix
Classifier: Operating System :: MacOS :: MacOS X
Classifier: Operating System :: Microsoft :: Windows
Requires-Python: >=3.10
License-File: LICENSE
Requires-Dist: cryptography>=41.0.1
Requires-Dist: numpy>=1.25.2
Requires-Dist: orjson>=3.10.2
Requires-Dist: pandas>=2.1.0
Dynamic: license-file
